Metadata-Version: 2.1
Name: folder-structure-generator-7edge
Version: 1.0.0
Summary: CLI tool to generate folder structures for services
Home-page: https://github.com/yourusername/folder-structure-generator-7edge
Author: Your Name
Author-email: your.email@example.com
Classifier: Programming Language :: Python :: 3
Classifier: License :: OSI Approved :: MIT License
Classifier: Operating System :: OS Independent
Requires-Python: >=3.6
Requires-Dist: InquirerPy
